[
  {
    "rule": 1180,
    "rule_bits": [
      0,
      0,
      0,
      0,
      0,
      0,
      0,
      1,
      0,
      0,
      1,
      0,
      0,
      1,
      1,
      1,
      0,
      0
    ],
    "entropy": 1.0,
    "surprise": 0.24691060185432434,
    "pred": 0.6167131066322327,
    "epoch": 184,
    "cam": [
      30,
      32
    ]
  },
  {
    "rule": 4304,
    "rule_bits": [
      0,
      0,
      0,
      0,
      0,
      1,
      0,
      0,
      0,
      0,
      1,
      1,
      0,
      1,
      0,
      0,
      0,
      0
    ],
    "entropy": 0.9999999999999982,
    "surprise": 0.2546215057373047,
    "pred": 0.6229958534240723,
    "epoch": 249,
    "cam": [
      31,
      31
    ]
  },
  {
    "rule": 4816,
    "rule_bits": [
      0,
      0,
      0,
      0,
      0,
      1,
      0,
      0,
      1,
      0,
      1,
      1,
      0,
      1,
      0,
      0,
      0,
      0
    ],
    "entropy": 1.0,
    "surprise": 0.25396379828453064,
    "pred": 0.6204597353935242,
    "epoch": 250,
    "cam": [
      31,
      32
    ]
  },
  {
    "rule": 4233,
    "rule_bits": [
      0,
      0,
      0,
      0,
      0,
      1,
      0,
      0,
      0,
      0,
      1,
      0,
      0,
      0,
      1,
      0,
      0,
      1
    ],
    "entropy": 1.0,
    "surprise": 0.256930410861969,
    "pred": 0.6231982707977295,
    "epoch": 269,
    "cam": [
      30,
      32
    ]
  },
  {
    "rule": 12871,
    "rule_bits": [
      0,
      0,
      0,
      0,
      1,
      1,
      0,
      0,
      1,
      0,
      0,
      1,
      0,
      0,
      0,
      1,
      1,
      1
    ],
    "entropy": 1.0000000000000002,
    "surprise": 0.25348174571990967,
    "pred": 0.6128385663032532,
    "epoch": 284,
    "cam": [
      32,
      31
    ]
  },
  {
    "rule": 12744,
    "rule_bits": [
      0,
      0,
      0,
      0,
      1,
      1,
      0,
      0,
      0,
      1,
      1,
      1,
      0,
      0,
      1,
      0,
      0,
      0
    ],
    "entropy": 1.0000000000000822,
    "surprise": 0.2776975929737091,
    "pred": 0.6099892258644104,
    "epoch": 311,
    "cam": [
      31,
      31
    ]
  },
  {
    "rule": 9173,
    "rule_bits": [
      0,
      0,
      0,
      0,
      1,
      0,
      0,
      0,
      1,
      1,
      1,
      1,
      0,
      1,
      0,
      1,
      0,
      1
    ],
    "entropy": 1.0000000000000682,
    "surprise": 0.25326675176620483,
    "pred": 0.6235561966896057,
    "epoch": 319,
    "cam": [
      31,
      32
    ]
  },
  {
    "rule": 3640,
    "rule_bits": [
      0,
      0,
      0,
      0,
      0,
      0,
      1,
      1,
      1,
      0,
      0,
      0,
      1,
      1,
      1,
      0,
      0,
      0
    ],
    "entropy": 1.0,
    "surprise": 0.24765516817569733,
    "pred": 0.6243442296981812,
    "epoch": 393,
    "cam": [
      31,
      32
    ]
  },
  {
    "rule": 11440,
    "rule_bits": [
      0,
      0,
      0,
      0,
      1,
      0,
      1,
      1,
      0,
      0,
      1,
      0,
      1,
      1,
      0,
      0,
      0,
      0
    ],
    "entropy": 0.9999999999999994,
    "surprise": 0.2530590891838074,
    "pred": 0.589741051197052,
    "epoch": 413,
    "cam": [
      31,
      31
    ]
  },
  {
    "rule": 653,
    "rule_bits": [
      0,
      0,
      0,
      0,
      0,
      0,
      0,
      0,
      1,
      0,
      1,
      0,
      0,
      0,
      1,
      1,
      0,
      1
    ],
    "entropy": 1.0000000000000002,
    "surprise": 0.23767367005348206,
    "pred": 0.598678708076477,
    "epoch": 450,
    "cam": [
      30,
      32
    ]
  },
  {
    "rule": 2263,
    "rule_bits": [
      0,
      0,
      0,
      0,
      0,
      0,
      1,
      0,
      0,
      0,
      1,
      1,
      0,
      1,
      0,
      1,
      1,
      1
    ],
    "entropy": 1.0000000000000453,
    "surprise": 0.25126928091049194,
    "pred": 0.5939494967460632,
    "epoch": 520,
    "cam": [
      32,
      32
    ]
  },
  {
    "rule": 6258,
    "rule_bits": [
      0,
      0,
      0,
      0,
      0,
      1,
      1,
      0,
      0,
      0,
      0,
      1,
      1,
      1,
      0,
      0,
      1,
      0
    ],
    "entropy": 1.0000000000000455,
    "surprise": 0.24265804886817932,
    "pred": 0.6116807460784912,
    "epoch": 531,
    "cam": [
      31,
      31
    ]
  },
  {
    "rule": 6250,
    "rule_bits": [
      0,
      0,
      0,
      0,
      0,
      1,
      1,
      0,
      0,
      0,
      0,
      1,
      1,
      0,
      1,
      0,
      1,
      0
    ],
    "entropy": 0.9999999999999986,
    "surprise": 0.24579977989196777,
    "pred": 0.6196900606155396,
    "epoch": 537,
    "cam": [
      31,
      30
    ]
  },
  {
    "rule": 6242,
    "rule_bits": [
      0,
      0,
      0,
      0,
      0,
      1,
      1,
      0,
      0,
      0,
      0,
      1,
      1,
      0,
      0,
      0,
      1,
      0
    ],
    "entropy": 1.0000000000000009,
    "surprise": 0.25012966990470886,
    "pred": 0.6297724843025208,
    "epoch": 544,
    "cam": [
      31,
      30
    ]
  },
  {
    "rule": 14449,
    "rule_bits": [
      0,
      0,
      0,
      0,
      1,
      1,
      1,
      0,
      0,
      0,
      0,
      1,
      1,
      1,
      0,
      0,
      0,
      1
    ],
    "entropy": 2.0000000000000004,
    "surprise": 0.1483049988746643,
    "pred": 0.6169260144233704,
    "epoch": 566,
    "cam": [
      31,
      31
    ]
  },
  {
    "rule": 21899,
    "rule_bits": [
      0,
      0,
      0,
      1,
      0,
      1,
      0,
      1,
      0,
      1,
      1,
      0,
      0,
      0,
      1,
      0,
      1,
      1
    ],
    "entropy": 1.0,
    "surprise": 0.21565088629722595,
    "pred": 0.6291000843048096,
    "epoch": 709,
    "cam": [
      30,
      31
    ]
  },
  {
    "rule": 1931,
    "rule_bits": [
      0,
      0,
      0,
      0,
      0,
      0,
      0,
      1,
      1,
      1,
      1,
      0,
      0,
      0,
      1,
      0,
      1,
      1
    ],
    "entropy": 0.9999999999999969,
    "surprise": 0.2580786645412445,
    "pred": 0.585540771484375,
    "epoch": 854,
    "cam": [
      31,
      30
    ]
  },
  {
    "rule": 2444,
    "rule_bits": [
      0,
      0,
      0,
      0,
      0,
      0,
      1,
      0,
      0,
      1,
      1,
      0,
      0,
      0,
      1,
      1,
      0,
      0
    ],
    "entropy": 0.9999999999999999,
    "surprise": 0.28436964750289917,
    "pred": 0.669611930847168,
    "epoch": 886,
    "cam": [
      31,
      31
    ]
  },
  {
    "rule": 11652,
    "rule_bits": [
      0,
      0,
      0,
      0,
      1,
      0,
      1,
      1,
      0,
      1,
      1,
      0,
      0,
      0,
      0,
      1,
      0,
      0
    ],
    "entropy": 0.9999999999999958,
    "surprise": 0.23146483302116394,
    "pred": 0.588241457939148,
    "epoch": 899,
    "cam": [
      31,
      31
    ]
  },
  {
    "rule": 12164,
    "rule_bits": [
      0,
      0,
      0,
      0,
      1,
      0,
      1,
      1,
      1,
      1,
      1,
      0,
      0,
      0,
      0,
      1,
      0,
      0
    ],
    "entropy": 1.0000000000000857,
    "surprise": 0.22014287114143372,
    "pred": 0.747148871421814,
    "epoch": 900,
    "cam": [
      31,
      31
    ]
  },
  {
    "rule": 9091,
    "rule_bits": [
      0,
      0,
      0,
      0,
      1,
      0,
      0,
      0,
      1,
      1,
      1,
      0,
      0,
      0,
      0,
      0,
      1,
      1
    ],
    "entropy": 0.999999999999998,
    "surprise": 0.18624259531497955,
    "pred": 0.5191625952720642,
    "epoch": 979,
    "cam": [
      31,
      31
    ]
  },
  {
    "rule": 9099,
    "rule_bits": [
      0,
      0,
      0,
      0,
      1,
      0,
      0,
      0,
      1,
      1,
      1,
      0,
      0,
      0,
      1,
      0,
      1,
      1
    ],
    "entropy": 1.0000000000000724,
    "surprise": 0.19364461302757263,
    "pred": 0.5854471921920776,
    "epoch": 986,
    "cam": [
      31,
      31
    ]
  }
]